prism/__init__.py
prism/analyzer.py
prism/classifier.py
prism/cli.py
prism/config.py
prism/parser.py
prism/processor.py
prism/rules.py
prism/types.py
prism_blanklines-0.5.6.dist-info/METADATA
prism_blanklines-0.5.6.dist-info/WHEEL
prism_blanklines-0.5.6.dist-info/entry_points.txt
prism_blanklines-0.5.6.dist-info/licenses/AUTHORS
prism_blanklines-0.5.6.dist-info/licenses/LICENSE
prism_blanklines-0.5.6.dist-info/RECORD
