Metadata-Version: 2.4
Name: prism-blanklines
Version: 0.5.6
Summary: Blank line enforcement for Python code based on CLAUDE.md rules
Project-URL: Repository, https://github.com/gsmethells/prism
Project-URL: Issues, https://github.com/gsmethells/prism/issues
Author: Greg Smethells
License: GPL-3.0-or-later
License-File: AUTHORS
License-File: LICENSE
Keywords: blank-lines,code-quality,formatter,python
Classifier: Development Status :: 3 - Alpha
Classifier: Intended Audience :: Developers
Classifier: Programming Language :: Python :: 3
Classifier: Programming Language :: Python :: 3.11
Classifier: Programming Language :: Python :: 3.12
Requires-Python: >=3.11
